[
  {
    "title": "Экстренная психологическая служба МЧС России",
    "description": "Предоставляет экстренную и анонимную помощь психологов круглосуточно для жителей всех регионов страны.",
    "phone": "+7 495 989-50-50"
  },
  {
    "title": "Консультации благотворительного фонда «Просто люди»",
    "description": "Фонд предлагает помощь людям с ментальными расстройствами и психологическими сложностями через консультации специалистов.",
    "phone": "+7 495 025-15-35"
  },
  {
    "title": "Телефон проекта «Прямой диалог»",
    "description": "Оказывает психологическую помощь мужчинам, столкнувшимся с жизненными трудностями, дистанционно.",
    "phone": "8 800 707-54-15"
  },
  {
    "title": "Онлайн-консультации психологического центра «Я — актив»",
    "description": "Бесплатная помощь людям в сложных жизненных ситуациях через онлайн-консультации.",
    "phone": "Узнать подробности"
  },
  {
    "title": "Телефон доверия центра «Сестры»",
    "description": "Помощь пережившим сексуализированное насилие и их родственникам, включая психологическую и юридическую поддержку.",
    "phone": "+7 499 901-02-01"
  },
  {
    "title": "Чат «Твоя территория.онлайн»",
    "description": "Консультация для подростков и молодежи до 23 лет в формате онлайн-переписки.",
    "phone": "Узнать подробности"
  },
  {
    "title": "Консультации проекта «Ярославна»",
    "description": "Психологическая помощь женщинам с возможностью очных встреч после диагностики.",
    "phone": "+7 495 120-16-60"
  },
  {
    "title": "Психологический университет для родителей от МГППУ",
    "description": "Бесплатные консультации по вопросам воспитания детей через круглосуточную горячую линию.",
    "phone": "Горячая линия: 8 800 444-22-34"
  },
  {
    "title": "Онлайн-консультации «Тебе поверят»",
    "description": "Психологическая помощь людям до 20 лет, столкнувшимся с сексуализированным насилием.",
    "phone": "Узнать подробности"
  },
  {
    "title": "Горячая линия фонда «Люди — людям»",
    "description": "Бесплатная психологическая помощь взрослым с тяжелыми заболеваниями и их родственникам.",
    "phone": "8 800 201-76-10"
  },
  {
    "title": "Вопросы психологу на «Психинфо»",
    "description": "Возможность задать письменный вопрос психологу, на который ответят несколько специалистов.",
    "phone": "Узнать подробности"
  },
  {
    "title": "Горячая линия «Ясное утро»",
    "description": "Запись на онлайн-консультацию и получение бесплатных очных консультаций для определенных категорий граждан.",
    "phone": "8 800 100-01-91"
  },
  {
    "title": "Онлайн-консультации проекта «Помогая другим — помогаешь себе»",
    "description": "Психологическая помощь от психологов с инвалидностью для людей в трудных жизненных ситуациях.",
    "phone": "Узнать подробности"
  },
  {
    "title": "Консультации выпускников Института практической психологии и психоанализа",
    "description": "Бесплатные консультации для желающих, как в офисе, так и онлайн.",
    "phone": "+7 495 646-11-08, +7 495 414-36-81"
  },
  {
    "title": "Горячая линия проекта «Без паники»",
    "description": "Экстренная психологическая помощь для взрослых по любым вопросам, включая любовные переживания и утрату.",
    "phone": "8 800 600-41-79"
  }
]
